flake8_too_many/__init__.py
flake8_too_many/checker.py
flake8_too_many/messages.py
flake8_too_many/options.py
flake8_too_many/utils/__init__.py
flake8_too_many/utils/function_arguments.py
flake8_too_many/utils/function_return_stmts.py
flake8_too_many/utils/function_return_values.py
flake8_too_many/utils/unpacking_targets.py
flake8_too_many/visitor.py
flake8_too_many-0.1.5.dist-info/entry_points.txt
flake8_too_many-0.1.5.dist-info/LICENSE
flake8_too_many-0.1.5.dist-info/WHEEL
flake8_too_many-0.1.5.dist-info/METADATA
flake8_too_many-0.1.5.dist-info/RECORD
