Metadata-Version: 2.1
Name: flake8-too-many
Version: 0.1.5
Summary: A flake8 plugin that prevents you from writing "too many" bad codes.
Home-page: https://github.com/queensferryme/flake8-too-many
License: MIT
Keywords: code quality,flake8,linting,plugin
Author: Queensferry
Author-email: queensferry.me@gmail.com
Requires-Python: >=3.7.0,<4.0.0
Classifier: Environment :: Console
Classifier: Framework :: Flake8
Classifier: Intended Audience :: Developers
Classifier: License :: OSI Approved :: MIT License
Classifier: Operating System :: OS Independent
Classifier: Programming Language :: Python
Classifier: Programming Language :: Python :: 3
Classifier: Programming Language :: Python :: 3.7
Classifier: Programming Language :: Python :: 3.8
Classifier: Programming Language :: Python :: 3.9
Classifier: Programming Language :: Python :: 3.10
Classifier: Programming Language :: Python :: 3
Classifier: Topic :: Software Development :: Libraries :: Python Modules
Classifier: Topic :: Software Development :: Quality Assurance
Requires-Dist: dataclasses (>=0.8,<0.9); python_version < "3.7"
Requires-Dist: flake8 (>=5.0.0,<6.0.0)
Project-URL: Repository, https://github.com/queensferryme/flake8-too-many
